{
  "name": "Trackr ITAM Dashboard Layout",
  "type": "DOCUMENT",
  "version": "1.0.0",
  "children": [
    {
      "id": "dashboard-page",
      "name": "Main Dashboard",
      "type": "CANVAS",
      "backgroundColor": "#F8FAFC",
      "children": [
        {
          "id": "dashboard-container",
          "name": "Dashboard Container",
          "type": "FRAME",
          "layoutMode": "VERTICAL",
          "padding": { "top": 24, "right": 24, "bottom": 24, "left": 24 },
          "itemSpacing": 24,
          "constraints": {
            "horizontal": "STRETCH",
            "vertical": "STRETCH"
          },
          "children": [
            {
              "id": "dashboard-header",
              "name": "Header Section",
              "type": "FRAME",
              "layoutMode": "HORIZONTAL",
              "padding": { "top": 16, "right": 24, "bottom": 16, "left": 24 },
              "itemSpacing": 16,
              "constraints": {
                "horizontal": "STRETCH",
                "vertical": "TOP"
              },
              "children": [
                {
                  "id": "header-title",
                  "name": "Dashboard Title",
                  "type": "TEXT",
                  "characters": "IT Asset Management Dashboard",
                  "style": {
                    "fontSize": 32,
                    "fontWeight": 700,
                    "color": "#0F172A"
                  }
                }
              ]
            },
            {
              "id": "main-grid",
              "name": "Main Grid Layout",
              "type": "FRAME",
              "layoutMode": "VERTICAL",
              "itemSpacing": 24,
              "constraints": {
                "horizontal": "STRETCH",
                "vertical": "STRETCH"
              },
              "children": [
                {
                  "id": "top-row",
                  "name": "Top Row - Asset List & Compliance Gauge",
                  "type": "FRAME",
                  "layoutMode": "HORIZONTAL",
                  "itemSpacing": 24,
                  "constraints": {
                    "horizontal": "STRETCH",
                    "vertical": "TOP"
                  },
                  "children": [
                    {
                      "id": "asset-list-container",
                      "name": "Asset List Container",
                      "type": "FRAME",
                      "layoutMode": "VERTICAL",
                      "padding": { "top": 24, "right": 24, "bottom": 24, "left": 24 },
                      "constraints": {
                        "horizontal": "FILL",
                        "vertical": "STRETCH"
                      },
                      "flex": 2,
                      "fills": [{ "type": "SOLID", "color": "#FFFFFF" }],
                      "cornerRadius": 16,
                      "effects": [
                        {
                          "type": "DROP_SHADOW",
                          "color": "#00000008",
                          "offset": { "x": 0, "y": 4 },
                          "radius": 12,
                          "spread": 0
                        }
                      ],
                      "children": [
                        {
                          "id": "asset-list-header",
                          "name": "Asset List Header",
                          "type": "FRAME",
                          "layoutMode": "HORIZONTAL",
                          "padding": { "top": 0, "right": 0, "bottom": 16, "left": 0 },
                          "itemSpacing": 12,
                          "children": [
                            {
                              "id": "asset-list-title",
                              "name": "Asset List Title",
                              "type": "TEXT",
                              "characters": "Asset Inventory",
                              "style": {
                                "fontSize": 20,
                                "fontWeight": 600,
                                "color": "#0F172A"
                              }
                            }
                          ]
                        },
                        {
                          "id": "asset-list-content",
                          "name": "Asset List Content",
                          "type": "FRAME",
                          "layoutMode": "VERTICAL",
                          "itemSpacing": 12,
                          "constraints": {
                            "horizontal": "STRETCH",
                            "vertical": "FILL"
                          },
                          "children": [
                            {
                              "id": "asset-card-placeholder-1",
                              "name": "Asset Card 1",
                              "type": "FRAME",
                              "layoutMode": "HORIZONTAL",
                              "padding": { "top": 16, "right": 16, "bottom": 16, "left": 16 },
                              "itemSpacing": 12,
                              "constraints": {
                                "horizontal": "STRETCH",
                                "vertical": "TOP"
                              },
                              "fills": [{ "type": "SOLID", "color": "#F8FAFC" }],
                              "cornerRadius": 12,
                              "children": []
                            },
                            {
                              "id": "asset-card-placeholder-2",
                              "name": "Asset Card 2",
                              "type": "FRAME",
                              "layoutMode": "HORIZONTAL",
                              "padding": { "top": 16, "right": 16, "bottom": 16, "left": 16 },
                              "itemSpacing": 12,
                              "constraints": {
                                "horizontal": "STRETCH",
                                "vertical": "TOP"
                              },
                              "fills": [{ "type": "SOLID", "color": "#F8FAFC" }],
                              "cornerRadius": 12,
                              "children": []
                            },
                            {
                              "id": "asset-card-placeholder-3",
                              "name": "Asset Card 3",
                              "type": "FRAME",
                              "layoutMode": "HORIZONTAL",
                              "padding": { "top": 16, "right": 16, "bottom": 16, "left": 16 },
                              "itemSpacing": 12,
                              "constraints": {
                                "horizontal": "STRETCH",
                                "vertical": "TOP"
                              },
                              "fills": [{ "type": "SOLID", "color": "#F8FAFC" }],
                              "cornerRadius": 12,
                              "children": []
                            }
                          ]
                        }
                      ]
                    },
                    {
                      "id": "compliance-gauge-container",
                      "name": "Compliance Gauge Container",
                      "type": "FRAME",
                      "layoutMode": "VERTICAL",
                      "padding": { "top": 24, "right": 24, "bottom": 24, "left": 24 },
                      "constraints": {
                        "horizontal": "FILL",
                        "vertical": "STRETCH"
                      },
                      "flex": 1,
                      "fills": [{ "type": "SOLID", "color": "#FFFFFF" }],
                      "cornerRadius": 16,
                      "effects": [
                        {
                          "type": "DROP_SHADOW",
                          "color": "#00000008",
                          "offset": { "x": 0, "y": 4 },
                          "radius": 12,
                          "spread": 0
                        }
                      ],
                      "children": [
                        {
                          "id": "compliance-gauge-header",
                          "name": "Compliance Gauge Header",
                          "type": "FRAME",
                          "layoutMode": "HORIZONTAL",
                          "padding": { "top": 0, "right": 0, "bottom": 16, "left": 0 },
                          "children": [
                            {
                              "id": "compliance-gauge-title",
                              "name": "Compliance Gauge Title",
                              "type": "TEXT",
                              "characters": "Compliance Status",
                              "style": {
                                "fontSize": 20,
                                "fontWeight": 600,
                                "color": "#0F172A"
                              }
                            }
                          ]
                        },
                        {
                          "id": "compliance-gauge-content",
                          "name": "Compliance Gauge Content",
                          "type": "FRAME",
                          "layoutMode": "VERTICAL",
                          "itemSpacing": 16,
                          "constraints": {
                            "horizontal": "STRETCH",
                            "vertical": "FILL"
                          },
                          "children": [
                            {
                              "id": "gauge-circle",
                              "name": "Gauge Circle Placeholder",
                              "type": "ELLIPSE",
                              "constraints": {
                                "horizontal": "CENTER",
                                "vertical": "CENTER"
                              },
                              "fills": [{ "type": "SOLID", "color": "#E2E8F0" }],
                              "stroke": {
                                "type": "SOLID",
                                "color": "#CBD5E1",
                                "width": 4
                              }
                            }
                          ]
                        }
                      ]
                    }
                  ],
                  "responsive": {
                    "sm": {
                      "layoutMode": "VERTICAL",
                      "itemSpacing": 16
                    },
                    "md": {
                      "layoutMode": "HORIZONTAL",
                      "itemSpacing": 24
                    },
                    "lg": {
                      "layoutMode": "HORIZONTAL",
                      "itemSpacing": 24
                    }
                  }
                },
                {
                  "id": "bottom-row",
                  "name": "Bottom Row - License Expiry Heatmap",
                  "type": "FRAME",
                  "layoutMode": "HORIZONTAL",
                  "itemSpacing": 24,
                  "constraints": {
                    "horizontal": "STRETCH",
                    "vertical": "FILL"
                  },
                  "children": [
                    {
                      "id": "license-heatmap-container",
                      "name": "License Expiry Heatmap Container",
                      "type": "FRAME",
                      "layoutMode": "VERTICAL",
                      "padding": { "top": 24, "right": 24, "bottom": 24, "left": 24 },
                      "constraints": {
                        "horizontal": "STRETCH",
                        "vertical": "STRETCH"
                      },
                      "flex": 1,
                      "fills": [{ "type": "SOLID", "color": "#FFFFFF" }],
                      "cornerRadius": 16,
                      "effects": [
                        {
                          "type": "DROP_SHADOW",
                          "color": "#00000008",
                          "offset": { "x": 0, "y": 4 },
                          "radius": 12,
                          "spread": 0
                        }
                      ],
                      "children": [
                        {
                          "id": "heatmap-header",
                          "name": "Heatmap Header",
                          "type": "FRAME",
                          "layoutMode": "HORIZONTAL",
                          "padding": { "top": 0, "right": 0, "bottom": 16, "left": 0 },
                          "itemSpacing": 12,
                          "children": [
                            {
                              "id": "heatmap-title",
                              "name": "Heatmap Title",
                              "type": "TEXT",
                              "characters": "License Expiry Heatmap",
                              "style": {
                                "fontSize": 20,
                                "fontWeight": 600,
                                "color": "#0F172A"
                              }
                            }
                          ]
                        },
                        {
                          "id": "heatmap-content",
                          "name": "Heatmap Content",
                          "type": "FRAME",
                          "layoutMode": "GRID",
                          "padding": { "top": 16, "right": 16, "bottom": 16, "left": 16 },
                          "itemSpacing": 8,
                          "gridColumns": 12,
                          "constraints": {
                            "horizontal": "STRETCH",
                            "vertical": "FILL"
                          },
                          "children": [
                            {
                              "id": "heatmap-cell-placeholder",
                              "name": "Heatmap Cell Placeholder",
                              "type": "FRAME",
                              "constraints": {
                                "horizontal": "FILL",
                                "vertical": "FILL"
                              },
                              "fills": [{ "type": "SOLID", "color": "#E2E8F0" }],
                              "cornerRadius": 4,
                              "children": []
                            }
                          ]
                        },
                        {
                          "id": "heatmap-legend",
                          "name": "Heatmap Legend",
                          "type": "FRAME",
                          "layoutMode": "HORIZONTAL",
                          "padding": { "top": 16, "right": 0, "bottom": 0, "left": 0 },
                          "itemSpacing": 16,
                          "constraints": {
                            "horizontal": "CENTER",
                            "vertical": "BOTTOM"
                          },
                          "children": [
                            {
                              "id": "legend-item-expired",
                              "name": "Legend - Expired",
                              "type": "FRAME",
                              "layoutMode": "HORIZONTAL",
                              "itemSpacing": 8,
                              "children": [
                                {
                                  "id": "legend-color-expired",
                                  "name": "Legend Color - Expired",
                                  "type": "RECTANGLE",
                                  "fills": [{ "type": "SOLID", "color": "#DC2626" }],
                                  "cornerRadius": 4
                                },
                                {
                                  "id": "legend-label-expired",
                                  "name": "Legend Label - Expired",
                                  "type": "TEXT",
                                  "characters": "Expired",
                                  "style": {
                                    "fontSize": 12,
                                    "fontWeight": 400,
                                    "color": "#64748B"
                                  }
                                }
                              ]
                            },
                            {
                              "id": "legend-item-expiring-soon",
                              "name": "Legend - Expiring Soon",
                              "type": "FRAME",
                              "layoutMode": "HORIZONTAL",
                              "itemSpacing": 8,
                              "children": [
                                {
                                  "id": "legend-color-expiring-soon",
                                  "name": "Legend Color - Expiring Soon",
                                  "type": "RECTANGLE",
                                  "fills": [{ "type": "SOLID", "color": "#F59E0B" }],
                                  "cornerRadius": 4
                                },
                                {
                                  "id": "legend-label-expiring-soon",
                                  "name": "Legend Label - Expiring Soon",
                                  "type": "TEXT",
                                  "characters": "Expiring Soon",
                                  "style": {
                                    "fontSize": 12,
                                    "fontWeight": 400,
                                    "color": "#64748B"
                                  }
                                }
                              ]
                            },
                            {
                              "id": "legend-item-valid",
                              "name": "Legend - Valid",
                              "type": "FRAME",
                              "layoutMode": "HORIZONTAL",
                              "itemSpacing": 8,
                              "children": [
                                {
                                  "id": "legend-color-valid",
                                  "name": "Legend Color - Valid",
                                  "type": "RECTANGLE",
                                  "fills": [{ "type": "SOLID", "color": "#10B981" }],
                                  "cornerRadius": 4
                                },
                                {
                                  "id": "legend-label-valid",
                                  "name": "Legend Label - Valid",
                                  "type": "TEXT",
                                  "characters": "Valid",
                                  "style": {
                                    "fontSize": 12,
                                    "fontWeight": 400,
                                    "color": "#64748B"
                                  }
                                }
                              ]
                            }
                          ]
                        }
                      ]
                    }
                  ]
                }
              ],
              "responsive": {
                "sm": {
                  "itemSpacing": 16
                },
                "md": {
                  "itemSpacing": 20
                },
                "lg": {
                  "itemSpacing": 24
                }
              }
            }
          ]
        }
      ]
    }
  ],
  "designTokens": {
    "colors": {
      "primary": {
        "50": "#F0F9FF",
        "500": "#0EA5E9",
        "600": "#0284C7"
      },
      "success": {
        "500": "#10B981"
      },
      "warning": {
        "500": "#F59E0B"
      },
      "danger": {
        "500": "#DC2626"
      },
      "neutral": {
        "50": "#F8FAFC",
        "100": "#F1F5F9",
        "200": "#E2E8F0",
        "600": "#475569",
        "900": "#0F172A"
      }
    },
    "spacing": {
      "xs": 4,
      "sm": 8,
      "md": 16,
      "lg": 24,
      "xl": 32
    },
    "borderRadius": {
      "sm": 8,
      "md": 12,
      "lg": 16,
      "xl": 24
    },
    "typography": {
      "heading": {
        "fontSize": 32,
        "fontWeight": 700,
        "lineHeight": 1.2
      },
      "subheading": {
        "fontSize": 20,
        "fontWeight": 600,
        "lineHeight": 1.4
      },
      "body": {
        "fontSize": 14,
        "fontWeight": 400,
        "lineHeight": 1.5
      }
    }
  },
  "responsiveBreakpoints": {
    "sm": 640,
    "md": 768,
    "lg": 1024,
    "xl": 1280
  }
}

